aliaro_i2c_device_control/__init__.py
aliaro_i2c_device_control-0.1.0.dist-info/METADATA
aliaro_i2c_device_control-0.1.0.dist-info/WHEEL
aliaro_i2c_device_control-0.1.0.dist-info/RECORD
